payflow/__init__.py
payflow/_version.py
payflow/client.py
payflow/errors.py
payflow/items.py
payflow/payments.py
payflow/responses.py
payflow-0.1.6.dist-info/LICENSE
payflow-0.1.6.dist-info/METADATA
payflow-0.1.6.dist-info/WHEEL
payflow-0.1.6.dist-info/top_level.txt
payflow-0.1.6.dist-info/RECORD
