Metadata-Version: 2.1
Name: payflow
Version: 0.1.6
Summary: Client for Flow Payment Acquirer
Home-page: https://gitlab.com/dansanti/payflow
Author: Daniel Santibáñez Polanco
Author-email: dansanti@gmail.com
License: GPLV3+
Classifier: Development Status :: 3 - Alpha
Classifier: License :: OSI Approved :: GNU General Public License v3 or later (GPLv3+)
Classifier: Programming Language :: Python :: 2.7
Classifier: Programming Language :: Python :: 3.6
Classifier: Intended Audience :: Developers
Classifier: Topic :: Software Development :: Libraries :: Python Modules
Classifier: Environment :: Console
License-File: LICENSE
Requires-Dist: urllib3
